README
setup.py
toMaKe/__init__.py
toMaKe/param.py
toMaKe/ui.py
toMaKe/util.py
toMaKe.egg-info/PKG-INFO
toMaKe.egg-info/SOURCES.txt
toMaKe.egg-info/dependency_links.txt
toMaKe.egg-info/pbr.json
toMaKe.egg-info/requires.txt
toMaKe.egg-info/top_level.txt