Metadata-Version: 1.1
Name: toMaKe
Version: 0.6.3
Summary: tools for Mad & Kea
Home-page: https://github.com/mfiers/toMaKe
Author: Mark Fiers
Author-email: mark.fiers.42@gmail.com
License: UNKNOWN
Platform: UNKNOWN
Classifier: Development Status :: 4 - Beta
Classifier: Environment :: Console
Classifier: Operating System :: OS Independent
Classifier: Programming Language :: Python
Classifier: Programming Language :: Python :: 2
Classifier: Programming Language :: Python :: 2.7
Classifier: Programming Language :: Python :: 3
Classifier: Programming Language :: Python :: 3.2
Classifier: Programming Language :: Python :: 3.3
Classifier: Programming Language :: Python :: 3.4
